login_jumper/__init__.py
login_jumper/cli.py
login_jumper/tests.py
login_jumper/bin/__init__.py
login_jumper/bin/jump.py
login_jumper/bin/jumper_expect.py
login_jumper/bin/server_gate.py
login_jumper/conf/config.ini
login_jumper/conf/redis.ini
login_jumper/logs/.gitfile
login_jumper/utils/__init__.py
login_jumper/utils/config.py
login_jumper/utils/get_logger.py
login_jumper/utils/jumper_info.py
login_jumper/utils/login_server.py
login_jumper/utils/my_redis.py
login_jumper/utils/terminal_size.py
login_jumper-2.1.5.data/data/login_jumper/conf/config.ini
login_jumper-2.1.5.data/data/login_jumper/conf/redis.ini
login_jumper-2.1.5.data/data/logs/.gitfile/.gitfile
login_jumper-2.1.5.dist-info/LICENSE
login_jumper-2.1.5.dist-info/METADATA
login_jumper-2.1.5.dist-info/WHEEL
login_jumper-2.1.5.dist-info/entry_points.txt
login_jumper-2.1.5.dist-info/top_level.txt
login_jumper-2.1.5.dist-info/RECORD
