Metadata-Version: 2.1
Name: login-jumper
Version: 2.1.5
Summary: Logging ecs automatic via jumper server
Home-page: https://github.com/sunnywalden/login-jumper
Author: SunnyWalden
Author-email: sunnywalden@gmail.com
License: UNKNOWN
Platform: any
Classifier: Programming Language :: Python :: 3
Classifier: License :: OSI Approved :: Apache Software License
Requires-Python: >=2.7
Requires-Dist: pycrypto
Requires-Dist: paramiko
Requires-Dist: pexpect
Requires-Dist: sentry-sdk
Requires-Dist: rollbar
Requires-Dist: redis
